[
  {
    "url": "https://api.github.com/repos/droboports/kernel-drobo5n/releases/1869902",
    "assets_url": "https://api.github.com/repos/droboports/kernel-drobo5n/releases/1869902/assets",
    "upload_url": "https://uploads.github.com/repos/droboports/kernel-drobo5n/releases/1869902/assets{?name,label}",
    "html_url": "https://github.com/droboports/kernel-drobo5n/releases/tag/v3.2.27-3.3.0",
    "id": 1869902,
    "tag_name": "v3.2.27-3.3.0",
    "target_commitish": "master",
    "name": "Kernel 3.2.27, firmware 3.3.0",
    "draft": false,
    "author": {
      "login": "ricardopadilha",
      "id": 1210756,
      "avatar_url": "https://avatars.githubusercontent.com/u/1210756?v=3",
      "gravatar_id": "",
      "url": "https://api.github.com/users/ricardopadilha",
      "html_url": "https://github.com/ricardopadilha",
      "followers_url": "https://api.github.com/users/ricardopadilha/followers",
      "following_url": "https://api.github.com/users/ricardopadilha/following{/other_user}",
      "gists_url": "https://api.github.com/users/ricardopadilha/gists{/gist_id}",
      "starred_url": "https://api.github.com/users/ricardopadilha/starred{/owner}{/repo}",
      "subscriptions_url": "https://api.github.com/users/ricardopadilha/subscriptions",
      "organizations_url": "https://api.github.com/users/ricardopadilha/orgs",
      "repos_url": "https://api.github.com/users/ricardopadilha/repos",
      "events_url": "https://api.github.com/users/ricardopadilha/events{/privacy}",
      "received_events_url": "https://api.github.com/users/ricardopadilha/received_events",
      "type": "User",
      "site_admin": false
    },
    "prerelease": false,
    "created_at": "2015-09-17T03:45:08Z",
    "published_at": "2015-09-25T20:13:31Z",
    "assets": [
      {
        "url": "https://api.github.com/repos/droboports/kernel-drobo5n/releases/assets/894468",
        "id": 894468,
        "name": "arc4.ko",
        "label": null,
        "uploader": {
          "login": "ricardopadilha",
          "id": 1210756,
          "avatar_url": "https://avatars.githubusercontent.com/u/1210756?v=3",
          "gravatar_id": "",
          "url": "https://api.github.com/users/ricardopadilha",
          "html_url": "https://github.com/ricardopadilha",
          "followers_url": "https://api.github.com/users/ricardopadilha/followers",
          "following_url": "https://api.github.com/users/ricardopadilha/following{/other_user}",
          "gists_url": "https://api.github.com/users/ricardopadilha/gists{/gist_id}",
          "starred_url": "https://api.github.com/users/ricardopadilha/starred{/owner}{/repo}",
          "subscriptions_url": "https://api.github.com/users/ricardopadilha/subscriptions",
          "organizations_url": "https://api.github.com/users/ricardopadilha/orgs",
          "repos_url": "https://api.github.com/users/ricardopadilha/repos",
          "events_url": "https://api.github.com/users/ricardopadilha/events{/privacy}",
          "received_events_url": "https://api.github.com/users/ricardopadilha/received_events",
          "type": "User",
          "site_admin": false
        },
        "content_type": "application/octet-stream",
        "state": "uploaded",
        "size": 39603,
        "download_count": 0,
        "created_at": "2015-09-25T20:12:48Z",
        "updated_at": "2015-09-25T20:12:51Z",
        "browser_download_url": "https://github.com/droboports/kernel-drobo5n/releases/download/v3.2.27-3.3.0/arc4.ko"
      },
      {
        "url": "https://api.github.com/repos/droboports/kernel-drobo5n/releases/assets/894469",
        "id": 894469,
        "name": "binfmt_misc.ko",
        "label": null,
        "uploader": {
          "login": "ricardopadilha",
          "id": 1210756,
          "avatar_url": "https://avatars.githubusercontent.com/u/1210756?v=3",
          "gravatar_id": "",
          "url": "https://api.github.com/users/ricardopadilha",
          "html_url": "https://github.com/ricardopadilha",
          "followers_url": "https://api.github.com/users/ricardopadilha/followers",
          "following_url": "https://api.github.com/users/ricardopadilha/following{/other_user}",
          "gists_url": "https://api.github.com/users/ricardopadilha/gists{/gist_id}",
          "starred_url": "https://api.github.com/users/ricardopadilha/starred{/owner}{/repo}",
          "subscriptions_url": "https://api.github.com/users/ricardopadilha/subscriptions",
          "organizations_url": "https://api.github.com/users/ricardopadilha/orgs",
          "repos_url": "https://api.github.com/users/ricardopadilha/repos",
          "events_url": "https://api.github.com/users/ricardopadilha/events{/privacy}",
          "received_events_url": "https://api.github.com/users/ricardopadilha/received_events",
          "type": "User",
          "site_admin": false
        },
        "content_type": "application/octet-stream",
        "state": "uploaded",
        "size": 127135,
        "download_count": 0,
        "created_at": "2015-09-25T20:12:48Z",
        "updated_at": "2015-09-25T20:12:53Z",
        "browser_download_url": "https://github.com/droboports/kernel-drobo5n/releases/download/v3.2.27-3.3.0/binfmt_misc.ko"
      },
      {
        "url": "https://api.github.com/repos/droboports/kernel-drobo5n/releases/assets/894470",
        "id": 894470,
        "name": "cifs.ko",
        "label": null,
        "uploader": {
          "login": "ricardopadilha",
          "id": 1210756,
          "avatar_url": "https://avatars.githubusercontent.com/u/1210756?v=3",
          "gravatar_id": "",
          "url": "https://api.github.com/users/ricardopadilha",
          "html_url": "https://github.com/ricardopadilha",
          "followers_url": "https://api.github.com/users/ricardopadilha/followers",
          "following_url": "https://api.github.com/users/ricardopadilha/following{/other_user}",
          "gists_url": "https://api.github.com/users/ricardopadilha/gists{/gist_id}",
          "starred_url": "https://api.github.com/users/ricardopadilha/starred{/owner}{/repo}",
          "subscriptions_url": "https://api.github.com/users/ricardopadilha/subscriptions",
          "organizations_url": "https://api.github.com/users/ricardopadilha/orgs",
          "repos_url": "https://api.github.com/users/ricardopadilha/repos",
          "events_url": "https://api.github.com/users/ricardopadilha/events{/privacy}",
          "received_events_url": "https://api.github.com/users/ricardopadilha/received_events",
          "type": "User",
          "site_admin": false
        },
        "content_type": "application/octet-stream",
        "state": "uploaded",
        "size": 3548719,
        "download_count": 0,
        "created_at": "2015-09-25T20:12:48Z",
        "updated_at": "2015-09-25T20:13:02Z",
        "browser_download_url": "https://github.com/droboports/kernel-drobo5n/releases/download/v3.2.27-3.3.0/cifs.ko"
      },
      {
        "url": "https://api.github.com/repos/droboports/kernel-drobo5n/releases/assets/894471",
        "id": 894471,
        "name": "crc-itu-t.ko",
        "label": null,
        "uploader": {
          "login": "ricardopadilha",
          "id": 1210756,
          "avatar_url": "https://avatars.githubusercontent.com/u/1210756?v=3",
          "gravatar_id": "",
          "url": "https://api.github.com/users/ricardopadilha",
          "html_url": "https://github.com/ricardopadilha",
          "followers_url": "https://api.github.com/users/ricardopadilha/followers",
          "following_url": "https://api.github.com/users/ricardopadilha/following{/other_user}",
          "gists_url": "https://api.github.com/users/ricardopadilha/gists{/gist_id}",
          "starred_url": "https://api.github.com/users/ricardopadilha/starred{/owner}{/repo}",
          "subscriptions_url": "https://api.github.com/users/ricardopadilha/subscriptions",
          "organizations_url": "https://api.github.com/users/ricardopadilha/orgs",
          "repos_url": "https://api.github.com/users/ricardopadilha/repos",
          "events_url": "https://api.github.com/users/ricardopadilha/events{/privacy}",
          "received_events_url": "https://api.github.com/users/ricardopadilha/received_events",
          "type": "User",
          "site_admin": false
        },
        "content_type": "application/octet-stream",
        "state": "uploaded",
        "size": 25555,
        "download_count": 0,
        "created_at": "2015-09-25T20:12:48Z",
        "updated_at": "2015-09-25T20:13:03Z",
        "browser_download_url": "https://github.com/droboports/kernel-drobo5n/releases/download/v3.2.27-3.3.0/crc-itu-t.ko"
      },
      {
        "url": "https://api.github.com/repos/droboports/kernel-drobo5n/releases/assets/894472",
        "id": 894472,
        "name": "cuse.ko",
        "label": null,
        "uploader": {
          "login": "ricardopadilha",
          "id": 1210756,
          "avatar_url": "https://avatars.githubusercontent.com/u/1210756?v=3",
          "gravatar_id": "",
          "url": "https://api.github.com/users/ricardopadilha",
          "html_url": "https://github.com/ricardopadilha",
          "followers_url": "https://api.github.com/users/ricardopadilha/followers",
          "following_url": "https://api.github.com/users/ricardopadilha/following{/other_user}",
          "gists_url": "https://api.github.com/users/ricardopadilha/gists{/gist_id}",
          "starred_url": "https://api.github.com/users/ricardopadilha/starred{/owner}{/repo}",
          "subscriptions_url": "https://api.github.com/users/ricardopadilha/subscriptions",
          "organizations_url": "https://api.github.com/users/ricardopadilha/orgs",
          "repos_url": "https://api.github.com/users/ricardopadilha/repos",
          "events_url": "https://api.github.com/users/ricardopadilha/events{/privacy}",
          "received_events_url": "https://api.github.com/users/ricardopadilha/received_events",
          "type": "User",
          "site_admin": false
        },
        "content_type": "application/octet-stream",
        "state": "uploaded",
        "size": 123983,
        "download_count": 0,
        "created_at": "2015-09-25T20:12:48Z",
        "updated_at": "2015-09-25T20:13:04Z",
        "browser_download_url": "https://github.com/droboports/kernel-drobo5n/releases/download/v3.2.27-3.3.0/cuse.ko"
      },
      {
        "url": "https://api.github.com/repos/droboports/kernel-drobo5n/releases/assets/894476",
        "id": 894476,
        "name": "ecb.ko",
        "label": null,
        "uploader": {
          "login": "ricardopadilha",
          "id": 1210756,
          "avatar_url": "https://avatars.githubusercontent.com/u/1210756?v=3",
          "gravatar_id": "",
          "url": "https://api.github.com/users/ricardopadilha",
          "html_url": "https://github.com/ricardopadilha",
          "followers_url": "https://api.github.com/users/ricardopadilha/followers",
          "following_url": "https://api.github.com/users/ricardopadilha/following{/other_user}",
          "gists_url": "https://api.github.com/users/ricardopadilha/gists{/gist_id}",
          "starred_url": "https://api.github.com/users/ricardopadilha/starred{/owner}{/repo}",
          "subscriptions_url": "https://api.github.com/users/ricardopadilha/subscriptions",
          "organizations_url": "https://api.github.com/users/ricardopadilha/orgs",
          "repos_url": "https://api.github.com/users/ricardopadilha/repos",
          "events_url": "https://api.github.com/users/ricardopadilha/events{/privacy}",
          "received_events_url": "https://api.github.com/users/ricardopadilha/received_events",
          "type": "User",
          "site_admin": false
        },
        "content_type": "application/octet-stream",
        "state": "uploaded",
        "size": 60825,
        "download_count": 0,
        "created_at": "2015-09-25T20:12:48Z",
        "updated_at": "2015-09-25T20:13:11Z",
        "browser_download_url": "https://github.com/droboports/kernel-drobo5n/releases/download/v3.2.27-3.3.0/ecb.ko"
      },
      {
        "url": "https://api.github.com/repos/droboports/kernel-drobo5n/releases/assets/894473",
        "id": 894473,
        "name": "fuse.ko",
        "label": null,
        "uploader": {
          "login": "ricardopadilha",
          "id": 1210756,
          "avatar_url": "https://avatars.githubusercontent.com/u/1210756?v=3",
          "gravatar_id": "",
          "url": "https://api.github.com/users/ricardopadilha",
          "html_url": "https://github.com/ricardopadilha",
          "followers_url": "https://api.github.com/users/ricardopadilha/followers",
          "following_url": "https://api.github.com/users/ricardopadilha/following{/other_user}",
          "gists_url": "https://api.github.com/users/ricardopadilha/gists{/gist_id}",
          "starred_url": "https://api.github.com/users/ricardopadilha/starred{/owner}{/repo}",
          "subscriptions_url": "https://api.github.com/users/ricardopadilha/subscriptions",
          "organizations_url": "https://api.github.com/users/ricardopadilha/orgs",
          "repos_url": "https://api.github.com/users/ricardopadilha/repos",
          "events_url": "https://api.github.com/users/ricardopadilha/events{/privacy}",
          "received_events_url": "https://api.github.com/users/ricardopadilha/received_events",
          "type": "User",
          "site_admin": false
        },
        "content_type": "application/octet-stream",
        "state": "uploaded",
        "size": 724175,
        "download_count": 0,
        "created_at": "2015-09-25T20:12:48Z",
        "updated_at": "2015-09-25T20:13:06Z",
        "browser_download_url": "https://github.com/droboports/kernel-drobo5n/releases/download/v3.2.27-3.3.0/fuse.ko"
      },
      {
        "url": "https://api.github.com/repos/droboports/kernel-drobo5n/releases/assets/894474",
        "id": 894474,
        "name": "nbd.ko",
        "label": null,
        "uploader": {
          "login": "ricardopadilha",
          "id": 1210756,
          "avatar_url": "https://avatars.githubusercontent.com/u/1210756?v=3",
          "gravatar_id": "",
          "url": "https://api.github.com/users/ricardopadilha",
          "html_url": "https://github.com/ricardopadilha",
          "followers_url": "https://api.github.com/users/ricardopadilha/followers",
          "following_url": "https://api.github.com/users/ricardopadilha/following{/other_user}",
          "gists_url": "https://api.github.com/users/ricardopadilha/gists{/gist_id}",
          "starred_url": "https://api.github.com/users/ricardopadilha/starred{/owner}{/repo}",
          "subscriptions_url": "https://api.github.com/users/ricardopadilha/subscriptions",
          "organizations_url": "https://api.github.com/users/ricardopadilha/orgs",
          "repos_url": "https://api.github.com/users/ricardopadilha/repos",
          "events_url": "https://api.github.com/users/ricardopadilha/events{/privacy}",
          "received_events_url": "https://api.github.com/users/ricardopadilha/received_events",
          "type": "User",
          "site_admin": false
        },
        "content_type": "application/octet-stream",
        "state": "uploaded",
        "size": 207718,
        "download_count": 0,
        "created_at": "2015-09-25T20:12:48Z",
        "updated_at": "2015-09-25T20:13:07Z",
        "browser_download_url": "https://github.com/droboports/kernel-drobo5n/releases/download/v3.2.27-3.3.0/nbd.ko"
      },
      {
        "url": "https://api.github.com/repos/droboports/kernel-drobo5n/releases/assets/894477",
        "id": 894477,
        "name": "nfsd.ko",
        "label": null,
        "uploader": {
          "login": "ricardopadilha",
          "id": 1210756,
          "avatar_url": "https://avatars.githubusercontent.com/u/1210756?v=3",
          "gravatar_id": "",
          "url": "https://api.github.com/users/ricardopadilha",
          "html_url": "https://github.com/ricardopadilha",
          "followers_url": "https://api.github.com/users/ricardopadilha/followers",
          "following_url": "https://api.github.com/users/ricardopadilha/following{/other_user}",
          "gists_url": "https://api.github.com/users/ricardopadilha/gists{/gist_id}",
          "starred_url": "https://api.github.com/users/ricardopadilha/starred{/owner}{/repo}",
          "subscriptions_url": "https://api.github.com/users/ricardopadilha/subscriptions",
          "organizations_url": "https://api.github.com/users/ricardopadilha/orgs",
          "repos_url": "https://api.github.com/users/ricardopadilha/repos",
          "events_url": "https://api.github.com/users/ricardopadilha/events{/privacy}",
          "received_events_url": "https://api.github.com/users/ricardopadilha/received_events",
          "type": "User",
          "site_admin": false
        },
        "content_type": "application/octet-stream",
        "state": "uploaded",
        "size": 1380435,
        "download_count": 3,
        "created_at": "2015-09-25T20:12:48Z",
        "updated_at": "2015-09-25T20:13:10Z",
        "browser_download_url": "https://github.com/droboports/kernel-drobo5n/releases/download/v3.2.27-3.3.0/nfsd.ko"
      },
      {
        "url": "https://api.github.com/repos/droboports/kernel-drobo5n/releases/assets/894475",
        "id": 894475,
        "name": "pcbc.ko",
        "label": null,
        "uploader": {
          "login": "ricardopadilha",
          "id": 1210756,
          "avatar_url": "https://avatars.githubusercontent.com/u/1210756?v=3",
          "gravatar_id": "",
          "url": "https://api.github.com/users/ricardopadilha",
          "html_url": "https://github.com/ricardopadilha",
          "followers_url": "https://api.github.com/users/ricardopadilha/followers",
          "following_url": "https://api.github.com/users/ricardopadilha/following{/other_user}",
          "gists_url": "https://api.github.com/users/ricardopadilha/gists{/gist_id}",
          "starred_url": "https://api.github.com/users/ricardopadilha/starred{/owner}{/repo}",
          "subscriptions_url": "https://api.github.com/users/ricardopadilha/subscriptions",
          "organizations_url": "https://api.github.com/users/ricardopadilha/orgs",
          "repos_url": "https://api.github.com/users/ricardopadilha/repos",
          "events_url": "https://api.github.com/users/ricardopadilha/events{/privacy}",
          "received_events_url": "https://api.github.com/users/ricardopadilha/received_events",
          "type": "User",
          "site_admin": false
        },
        "content_type": "application/octet-stream",
        "state": "uploaded",
        "size": 63950,
        "download_count": 0,
        "created_at": "2015-09-25T20:12:48Z",
        "updated_at": "2015-09-25T20:13:10Z",
        "browser_download_url": "https://github.com/droboports/kernel-drobo5n/releases/download/v3.2.27-3.3.0/pcbc.ko"
      },
      {
        "url": "https://api.github.com/repos/droboports/kernel-drobo5n/releases/assets/894478",
        "id": 894478,
        "name": "tun.ko",
        "label": null,
        "uploader": {
          "login": "ricardopadilha",
          "id": 1210756,
          "avatar_url": "https://avatars.githubusercontent.com/u/1210756?v=3",
          "gravatar_id": "",
          "url": "https://api.github.com/users/ricardopadilha",
          "html_url": "https://github.com/ricardopadilha",
          "followers_url": "https://api.github.com/users/ricardopadilha/followers",
          "following_url": "https://api.github.com/users/ricardopadilha/following{/other_user}",
          "gists_url": "https://api.github.com/users/ricardopadilha/gists{/gist_id}",
          "starred_url": "https://api.github.com/users/ricardopadilha/starred{/owner}{/repo}",
          "subscriptions_url": "https://api.github.com/users/ricardopadilha/subscriptions",
          "organizations_url": "https://api.github.com/users/ricardopadilha/orgs",
          "repos_url": "https://api.github.com/users/ricardopadilha/repos",
          "events_url": "https://api.github.com/users/ricardopadilha/events{/privacy}",
          "received_events_url": "https://api.github.com/users/ricardopadilha/received_events",
          "type": "User",
          "site_admin": false
        },
        "content_type": "application/octet-stream",
        "state": "uploaded",
        "size": 226150,
        "download_count": 0,
        "created_at": "2015-09-25T20:12:49Z",
        "updated_at": "2015-09-25T20:13:13Z",
        "browser_download_url": "https://github.com/droboports/kernel-drobo5n/releases/download/v3.2.27-3.3.0/tun.ko"
      }
    ],
    "tarball_url": "https://api.github.com/repos/droboports/kernel-drobo5n/tarball/v3.2.27-3.3.0",
    "zipball_url": "https://api.github.com/repos/droboports/kernel-drobo5n/zipball/v3.2.27-3.3.0",
    "body": "Kernel configuration updated to firmware 3.3.0.\r\n\r\nSee the [wiki](https://github.com/droboports/kernel-drobo5n/wiki) for compile instructions."
  },
  {
    "url": "https://api.github.com/repos/droboports/kernel-drobo5n/releases/1869831",
    "assets_url": "https://api.github.com/repos/droboports/kernel-drobo5n/releases/1869831/assets",
    "upload_url": "https://uploads.github.com/repos/droboports/kernel-drobo5n/releases/1869831/assets{?name,label}",
    "html_url": "https://github.com/droboports/kernel-drobo5n/releases/tag/v3.2.27-3.1.1",
    "id": 1869831,
    "tag_name": "v3.2.27-3.1.1",
    "target_commitish": "master",
    "name": "Kernel 3.2.27, firmware 3.1.1",
    "draft": false,
    "author": {
      "login": "ricardopadilha",
      "id": 1210756,
      "avatar_url": "https://avatars.githubusercontent.com/u/1210756?v=3",
      "gravatar_id": "",
      "url": "https://api.github.com/users/ricardopadilha",
      "html_url": "https://github.com/ricardopadilha",
      "followers_url": "https://api.github.com/users/ricardopadilha/followers",
      "following_url": "https://api.github.com/users/ricardopadilha/following{/other_user}",
      "gists_url": "https://api.github.com/users/ricardopadilha/gists{/gist_id}",
      "starred_url": "https://api.github.com/users/ricardopadilha/starred{/owner}{/repo}",
      "subscriptions_url": "https://api.github.com/users/ricardopadilha/subscriptions",
      "organizations_url": "https://api.github.com/users/ricardopadilha/orgs",
      "repos_url": "https://api.github.com/users/ricardopadilha/repos",
      "events_url": "https://api.github.com/users/ricardopadilha/events{/privacy}",
      "received_events_url": "https://api.github.com/users/ricardopadilha/received_events",
      "type": "User",
      "site_admin": false
    },
    "prerelease": false,
    "created_at": "2014-11-07T08:57:00Z",
    "published_at": "2015-09-25T19:54:58Z",
    "assets": [
      {
        "url": "https://api.github.com/repos/droboports/kernel-drobo5n/releases/assets/894434",
        "id": 894434,
        "name": "arc4.ko",
        "label": null,
        "uploader": {
          "login": "ricardopadilha",
          "id": 1210756,
          "avatar_url": "https://avatars.githubusercontent.com/u/1210756?v=3",
          "gravatar_id": "",
          "url": "https://api.github.com/users/ricardopadilha",
          "html_url": "https://github.com/ricardopadilha",
          "followers_url": "https://api.github.com/users/ricardopadilha/followers",
          "following_url": "https://api.github.com/users/ricardopadilha/following{/other_user}",
          "gists_url": "https://api.github.com/users/ricardopadilha/gists{/gist_id}",
          "starred_url": "https://api.github.com/users/ricardopadilha/starred{/owner}{/repo}",
          "subscriptions_url": "https://api.github.com/users/ricardopadilha/subscriptions",
          "organizations_url": "https://api.github.com/users/ricardopadilha/orgs",
          "repos_url": "https://api.github.com/users/ricardopadilha/repos",
          "events_url": "https://api.github.com/users/ricardopadilha/events{/privacy}",
          "received_events_url": "https://api.github.com/users/ricardopadilha/received_events",
          "type": "User",
          "site_admin": false
        },
        "content_type": "application/octet-stream",
        "state": "uploaded",
        "size": 39603,
        "download_count": 0,
        "created_at": "2015-09-25T20:00:59Z",
        "updated_at": "2015-09-25T20:01:03Z",
        "browser_download_url": "https://github.com/droboports/kernel-drobo5n/releases/download/v3.2.27-3.1.1/arc4.ko"
      },
      {
        "url": "https://api.github.com/repos/droboports/kernel-drobo5n/releases/assets/894437",
        "id": 894437,
        "name": "binfmt_misc.ko",
        "label": null,
        "uploader": {
          "login": "ricardopadilha",
          "id": 1210756,
          "avatar_url": "https://avatars.githubusercontent.com/u/1210756?v=3",
          "gravatar_id": "",
          "url": "https://api.github.com/users/ricardopadilha",
          "html_url": "https://github.com/ricardopadilha",
          "followers_url": "https://api.github.com/users/ricardopadilha/followers",
          "following_url": "https://api.github.com/users/ricardopadilha/following{/other_user}",
          "gists_url": "https://api.github.com/users/ricardopadilha/gists{/gist_id}",
          "starred_url": "https://api.github.com/users/ricardopadilha/starred{/owner}{/repo}",
          "subscriptions_url": "https://api.github.com/users/ricardopadilha/subscriptions",
          "organizations_url": "https://api.github.com/users/ricardopadilha/orgs",
          "repos_url": "https://api.github.com/users/ricardopadilha/repos",
          "events_url": "https://api.github.com/users/ricardopadilha/events{/privacy}",
          "received_events_url": "https://api.github.com/users/ricardopadilha/received_events",
          "type": "User",
          "site_admin": false
        },
        "content_type": "application/octet-stream",
        "state": "uploaded",
        "size": 118647,
        "download_count": 0,
        "created_at": "2015-09-25T20:01:36Z",
        "updated_at": "2015-09-25T20:01:38Z",
        "browser_download_url": "https://github.com/droboports/kernel-drobo5n/releases/download/v3.2.27-3.1.1/binfmt_misc.ko"
      },
      {
        "url": "https://api.github.com/repos/droboports/kernel-drobo5n/releases/assets/894442",
        "id": 894442,
        "name": "cifs.ko",
        "label": null,
        "uploader": {
          "login": "ricardopadilha",
          "id": 1210756,
          "avatar_url": "https://avatars.githubusercontent.com/u/1210756?v=3",
          "gravatar_id": "",
          "url": "https://api.github.com/users/ricardopadilha",
          "html_url": "https://github.com/ricardopadilha",
          "followers_url": "https://api.github.com/users/ricardopadilha/followers",
          "following_url": "https://api.github.com/users/ricardopadilha/following{/other_user}",
          "gists_url": "https://api.github.com/users/ricardopadilha/gists{/gist_id}",
          "starred_url": "https://api.github.com/users/ricardopadilha/starred{/owner}{/repo}",
          "subscriptions_url": "https://api.github.com/users/ricardopadilha/subscriptions",
          "organizations_url": "https://api.github.com/users/ricardopadilha/orgs",
          "repos_url": "https://api.github.com/users/ricardopadilha/repos",
          "events_url": "https://api.github.com/users/ricardopadilha/events{/privacy}",
          "received_events_url": "https://api.github.com/users/ricardopadilha/received_events",
          "type": "User",
          "site_admin": false
        },
        "content_type": "application/octet-stream",
        "state": "uploaded",
        "size": 3539467,
        "download_count": 0,
        "created_at": "2015-09-25T20:03:09Z",
        "updated_at": "2015-09-25T20:03:36Z",
        "browser_download_url": "https://github.com/droboports/kernel-drobo5n/releases/download/v3.2.27-3.1.1/cifs.ko"
      },
      {
        "url": "https://api.github.com/repos/droboports/kernel-drobo5n/releases/assets/894443",
        "id": 894443,
        "name": "cuse.ko",
        "label": null,
        "uploader": {
          "login": "ricardopadilha",
          "id": 1210756,
          "avatar_url": "https://avatars.githubusercontent.com/u/1210756?v=3",
          "gravatar_id": "",
          "url": "https://api.github.com/users/ricardopadilha",
          "html_url": "https://github.com/ricardopadilha",
          "followers_url": "https://api.github.com/users/ricardopadilha/followers",
          "following_url": "https://api.github.com/users/ricardopadilha/following{/other_user}",
          "gists_url": "https://api.github.com/users/ricardopadilha/gists{/gist_id}",
          "starred_url": "https://api.github.com/users/ricardopadilha/starred{/owner}{/repo}",
          "subscriptions_url": "https://api.github.com/users/ricardopadilha/subscriptions",
          "organizations_url": "https://api.github.com/users/ricardopadilha/orgs",
          "repos_url": "https://api.github.com/users/ricardopadilha/repos",
          "events_url": "https://api.github.com/users/ricardopadilha/events{/privacy}",
          "received_events_url": "https://api.github.com/users/ricardopadilha/received_events",
          "type": "User",
          "site_admin": false
        },
        "content_type": "application/octet-stream",
        "state": "uploaded",
        "size": 123467,
        "download_count": 0,
        "created_at": "2015-09-25T20:03:41Z",
        "updated_at": "2015-09-25T20:03:42Z",
        "browser_download_url": "https://github.com/droboports/kernel-drobo5n/releases/download/v3.2.27-3.1.1/cuse.ko"
      },
      {
        "url": "https://api.github.com/repos/droboports/kernel-drobo5n/releases/assets/894432",
        "id": 894432,
        "name": "ecb.ko",
        "label": null,
        "uploader": {
          "login": "ricardopadilha",
          "id": 1210756,
          "avatar_url": "https://avatars.githubusercontent.com/u/1210756?v=3",
          "gravatar_id": "",
          "url": "https://api.github.com/users/ricardopadilha",
          "html_url": "https://github.com/ricardopadilha",
          "followers_url": "https://api.github.com/users/ricardopadilha/followers",
          "following_url": "https://api.github.com/users/ricardopadilha/following{/other_user}",
          "gists_url": "https://api.github.com/users/ricardopadilha/gists{/gist_id}",
          "starred_url": "https://api.github.com/users/ricardopadilha/starred{/owner}{/repo}",
          "subscriptions_url": "https://api.github.com/users/ricardopadilha/subscriptions",
          "organizations_url": "https://api.github.com/users/ricardopadilha/orgs",
          "repos_url": "https://api.github.com/users/ricardopadilha/repos",
          "events_url": "https://api.github.com/users/ricardopadilha/events{/privacy}",
          "received_events_url": "https://api.github.com/users/ricardopadilha/received_events",
          "type": "User",
          "site_admin": false
        },
        "content_type": "application/octet-stream",
        "state": "uploaded",
        "size": 60825,
        "download_count": 0,
        "created_at": "2015-09-25T20:00:59Z",
        "updated_at": "2015-09-25T20:01:01Z",
        "browser_download_url": "https://github.com/droboports/kernel-drobo5n/releases/download/v3.2.27-3.1.1/ecb.ko"
      },
      {
        "url": "https://api.github.com/repos/droboports/kernel-drobo5n/releases/assets/894444",
        "id": 894444,
        "name": "fuse.ko",
        "label": null,
        "uploader": {
          "login": "ricardopadilha",
          "id": 1210756,
          "avatar_url": "https://avatars.githubusercontent.com/u/1210756?v=3",
          "gravatar_id": "",
          "url": "https://api.github.com/users/ricardopadilha",
          "html_url": "https://github.com/ricardopadilha",
          "followers_url": "https://api.github.com/users/ricardopadilha/followers",
          "following_url": "https://api.github.com/users/ricardopadilha/following{/other_user}",
          "gists_url": "https://api.github.com/users/ricardopadilha/gists{/gist_id}",
          "starred_url": "https://api.github.com/users/ricardopadilha/starred{/owner}{/repo}",
          "subscriptions_url": "https://api.github.com/users/ricardopadilha/subscriptions",
          "organizations_url": "https://api.github.com/users/ricardopadilha/orgs",
          "repos_url": "https://api.github.com/users/ricardopadilha/repos",
          "events_url": "https://api.github.com/users/ricardopadilha/events{/privacy}",
          "received_events_url": "https://api.github.com/users/ricardopadilha/received_events",
          "type": "User",
          "site_admin": false
        },
        "content_type": "application/octet-stream",
        "state": "uploaded",
        "size": 721087,
        "download_count": 0,
        "created_at": "2015-09-25T20:03:41Z",
        "updated_at": "2015-09-25T20:03:45Z",
        "browser_download_url": "https://github.com/droboports/kernel-drobo5n/releases/download/v3.2.27-3.1.1/fuse.ko"
      },
      {
        "url": "https://api.github.com/repos/droboports/kernel-drobo5n/releases/assets/894439",
        "id": 894439,
        "name": "nbd.ko",
        "label": null,
        "uploader": {
          "login": "ricardopadilha",
          "id": 1210756,
          "avatar_url": "https://avatars.githubusercontent.com/u/1210756?v=3",
          "gravatar_id": "",
          "url": "https://api.github.com/users/ricardopadilha",
          "html_url": "https://github.com/ricardopadilha",
          "followers_url": "https://api.github.com/users/ricardopadilha/followers",
          "following_url": "https://api.github.com/users/ricardopadilha/following{/other_user}",
          "gists_url": "https://api.github.com/users/ricardopadilha/gists{/gist_id}",
          "starred_url": "https://api.github.com/users/ricardopadilha/starred{/owner}{/repo}",
          "subscriptions_url": "https://api.github.com/users/ricardopadilha/subscriptions",
          "organizations_url": "https://api.github.com/users/ricardopadilha/orgs",
          "repos_url": "https://api.github.com/users/ricardopadilha/repos",
          "events_url": "https://api.github.com/users/ricardopadilha/events{/privacy}",
          "received_events_url": "https://api.github.com/users/ricardopadilha/received_events",
          "type": "User",
          "site_admin": false
        },
        "content_type": "application/octet-stream",
        "state": "uploaded",
        "size": 207198,
        "download_count": 0,
        "created_at": "2015-09-25T20:02:03Z",
        "updated_at": "2015-09-25T20:02:06Z",
        "browser_download_url": "https://github.com/droboports/kernel-drobo5n/releases/download/v3.2.27-3.1.1/nbd.ko"
      },
      {
        "url": "https://api.github.com/repos/droboports/kernel-drobo5n/releases/assets/894445",
        "id": 894445,
        "name": "nfsd.ko",
        "label": null,
        "uploader": {
          "login": "ricardopadilha",
          "id": 1210756,
          "avatar_url": "https://avatars.githubusercontent.com/u/1210756?v=3",
          "gravatar_id": "",
          "url": "https://api.github.com/users/ricardopadilha",
          "html_url": "https://github.com/ricardopadilha",
          "followers_url": "https://api.github.com/users/ricardopadilha/followers",
          "following_url": "https://api.github.com/users/ricardopadilha/following{/other_user}",
          "gists_url": "https://api.github.com/users/ricardopadilha/gists{/gist_id}",
          "starred_url": "https://api.github.com/users/ricardopadilha/starred{/owner}{/repo}",
          "subscriptions_url": "https://api.github.com/users/ricardopadilha/subscriptions",
          "organizations_url": "https://api.github.com/users/ricardopadilha/orgs",
          "repos_url": "https://api.github.com/users/ricardopadilha/repos",
          "events_url": "https://api.github.com/users/ricardopadilha/events{/privacy}",
          "received_events_url": "https://api.github.com/users/ricardopadilha/received_events",
          "type": "User",
          "site_admin": false
        },
        "content_type": "application/octet-stream",
        "state": "uploaded",
        "size": 1376903,
        "download_count": 3,
        "created_at": "2015-09-25T20:03:58Z",
        "updated_at": "2015-09-25T20:04:23Z",
        "browser_download_url": "https://github.com/droboports/kernel-drobo5n/releases/download/v3.2.27-3.1.1/nfsd.ko"
      },
      {
        "url": "https://api.github.com/repos/droboports/kernel-drobo5n/releases/assets/894433",
        "id": 894433,
        "name": "pcbc.ko",
        "label": null,
        "uploader": {
          "login": "ricardopadilha",
          "id": 1210756,
          "avatar_url": "https://avatars.githubusercontent.com/u/1210756?v=3",
          "gravatar_id": "",
          "url": "https://api.github.com/users/ricardopadilha",
          "html_url": "https://github.com/ricardopadilha",
          "followers_url": "https://api.github.com/users/ricardopadilha/followers",
          "following_url": "https://api.github.com/users/ricardopadilha/following{/other_user}",
          "gists_url": "https://api.github.com/users/ricardopadilha/gists{/gist_id}",
          "starred_url": "https://api.github.com/users/ricardopadilha/starred{/owner}{/repo}",
          "subscriptions_url": "https://api.github.com/users/ricardopadilha/subscriptions",
          "organizations_url": "https://api.github.com/users/ricardopadilha/orgs",
          "repos_url": "https://api.github.com/users/ricardopadilha/repos",
          "events_url": "https://api.github.com/users/ricardopadilha/events{/privacy}",
          "received_events_url": "https://api.github.com/users/ricardopadilha/received_events",
          "type": "User",
          "site_admin": false
        },
        "content_type": "application/octet-stream",
        "state": "uploaded",
        "size": 63950,
        "download_count": 0,
        "created_at": "2015-09-25T20:00:59Z",
        "updated_at": "2015-09-25T20:01:03Z",
        "browser_download_url": "https://github.com/droboports/kernel-drobo5n/releases/download/v3.2.27-3.1.1/pcbc.ko"
      },
      {
        "url": "https://api.github.com/repos/droboports/kernel-drobo5n/releases/assets/894440",
        "id": 894440,
        "name": "tun.ko",
        "label": null,
        "uploader": {
          "login": "ricardopadilha",
          "id": 1210756,
          "avatar_url": "https://avatars.githubusercontent.com/u/1210756?v=3",
          "gravatar_id": "",
          "url": "https://api.github.com/users/ricardopadilha",
          "html_url": "https://github.com/ricardopadilha",
          "followers_url": "https://api.github.com/users/ricardopadilha/followers",
          "following_url": "https://api.github.com/users/ricardopadilha/following{/other_user}",
          "gists_url": "https://api.github.com/users/ricardopadilha/gists{/gist_id}",
          "starred_url": "https://api.github.com/users/ricardopadilha/starred{/owner}{/repo}",
          "subscriptions_url": "https://api.github.com/users/ricardopadilha/subscriptions",
          "organizations_url": "https://api.github.com/users/ricardopadilha/orgs",
          "repos_url": "https://api.github.com/users/ricardopadilha/repos",
          "events_url": "https://api.github.com/users/ricardopadilha/events{/privacy}",
          "received_events_url": "https://api.github.com/users/ricardopadilha/received_events",
          "type": "User",
          "site_admin": false
        },
        "content_type": "application/octet-stream",
        "state": "uploaded",
        "size": 225634,
        "download_count": 0,
        "created_at": "2015-09-25T20:02:24Z",
        "updated_at": "2015-09-25T20:02:28Z",
        "browser_download_url": "https://github.com/droboports/kernel-drobo5n/releases/download/v3.2.27-3.1.1/tun.ko"
      }
    ],
    "tarball_url": "https://api.github.com/repos/droboports/kernel-drobo5n/tarball/v3.2.27-3.1.1",
    "zipball_url": "https://api.github.com/repos/droboports/kernel-drobo5n/zipball/v3.2.27-3.1.1",
    "body": "Kernel configuration from firmware 3.1.1.\r\n\r\nSee the [wiki](https://github.com/droboports/kernel-drobo5n/wiki) for compile instructions."
  },
  {
    "url": "https://api.github.com/repos/droboports/kernel-drobo5n/releases/946096",
    "assets_url": "https://api.github.com/repos/droboports/kernel-drobo5n/releases/946096/assets",
    "upload_url": "https://uploads.github.com/repos/droboports/kernel-drobo5n/releases/946096/assets{?name,label}",
    "html_url": "https://github.com/droboports/kernel-drobo5n/releases/tag/v3.2.27-3.2.0",
    "id": 946096,
    "tag_name": "v3.2.27-3.2.0",
    "target_commitish": "master",
    "name": "Kernel 3.2.27, firmware 3.2.0",
    "draft": false,
    "author": {
      "login": "ricardopadilha",
      "id": 1210756,
      "avatar_url": "https://avatars.githubusercontent.com/u/1210756?v=3",
      "gravatar_id": "",
      "url": "https://api.github.com/users/ricardopadilha",
      "html_url": "https://github.com/ricardopadilha",
      "followers_url": "https://api.github.com/users/ricardopadilha/followers",
      "following_url": "https://api.github.com/users/ricardopadilha/following{/other_user}",
      "gists_url": "https://api.github.com/users/ricardopadilha/gists{/gist_id}",
      "starred_url": "https://api.github.com/users/ricardopadilha/starred{/owner}{/repo}",
      "subscriptions_url": "https://api.github.com/users/ricardopadilha/subscriptions",
      "organizations_url": "https://api.github.com/users/ricardopadilha/orgs",
      "repos_url": "https://api.github.com/users/ricardopadilha/repos",
      "events_url": "https://api.github.com/users/ricardopadilha/events{/privacy}",
      "received_events_url": "https://api.github.com/users/ricardopadilha/received_events",
      "type": "User",
      "site_admin": false
    },
    "prerelease": false,
    "created_at": "2015-03-01T20:05:27Z",
    "published_at": "2015-09-25T20:07:39Z",
    "assets": [
      {
        "url": "https://api.github.com/repos/droboports/kernel-drobo5n/releases/assets/894450",
        "id": 894450,
        "name": "arc4.ko",
        "label": null,
        "uploader": {
          "login": "ricardopadilha",
          "id": 1210756,
          "avatar_url": "https://avatars.githubusercontent.com/u/1210756?v=3",
          "gravatar_id": "",
          "url": "https://api.github.com/users/ricardopadilha",
          "html_url": "https://github.com/ricardopadilha",
          "followers_url": "https://api.github.com/users/ricardopadilha/followers",
          "following_url": "https://api.github.com/users/ricardopadilha/following{/other_user}",
          "gists_url": "https://api.github.com/users/ricardopadilha/gists{/gist_id}",
          "starred_url": "https://api.github.com/users/ricardopadilha/starred{/owner}{/repo}",
          "subscriptions_url": "https://api.github.com/users/ricardopadilha/subscriptions",
          "organizations_url": "https://api.github.com/users/ricardopadilha/orgs",
          "repos_url": "https://api.github.com/users/ricardopadilha/repos",
          "events_url": "https://api.github.com/users/ricardopadilha/events{/privacy}",
          "received_events_url": "https://api.github.com/users/ricardopadilha/received_events",
          "type": "User",
          "site_admin": false
        },
        "content_type": "application/octet-stream",
        "state": "uploaded",
        "size": 39603,
        "download_count": 0,
        "created_at": "2015-09-25T20:06:56Z",
        "updated_at": "2015-09-25T20:06:58Z",
        "browser_download_url": "https://github.com/droboports/kernel-drobo5n/releases/download/v3.2.27-3.2.0/arc4.ko"
      },
      {
        "url": "https://api.github.com/repos/droboports/kernel-drobo5n/releases/assets/894452",
        "id": 894452,
        "name": "binfmt_misc.ko",
        "label": null,
        "uploader": {
          "login": "ricardopadilha",
          "id": 1210756,
          "avatar_url": "https://avatars.githubusercontent.com/u/1210756?v=3",
          "gravatar_id": "",
          "url": "https://api.github.com/users/ricardopadilha",
          "html_url": "https://github.com/ricardopadilha",
          "followers_url": "https://api.github.com/users/ricardopadilha/followers",
          "following_url": "https://api.github.com/users/ricardopadilha/following{/other_user}",
          "gists_url": "https://api.github.com/users/ricardopadilha/gists{/gist_id}",
          "starred_url": "https://api.github.com/users/ricardopadilha/starred{/owner}{/repo}",
          "subscriptions_url": "https://api.github.com/users/ricardopadilha/subscriptions",
          "organizations_url": "https://api.github.com/users/ricardopadilha/orgs",
          "repos_url": "https://api.github.com/users/ricardopadilha/repos",
          "events_url": "https://api.github.com/users/ricardopadilha/events{/privacy}",
          "received_events_url": "https://api.github.com/users/ricardopadilha/received_events",
          "type": "User",
          "site_admin": false
        },
        "content_type": "application/octet-stream",
        "state": "uploaded",
        "size": 127067,
        "download_count": 0,
        "created_at": "2015-09-25T20:06:56Z",
        "updated_at": "2015-09-25T20:07:14Z",
        "browser_download_url": "https://github.com/droboports/kernel-drobo5n/releases/download/v3.2.27-3.2.0/binfmt_misc.ko"
      },
      {
        "url": "https://api.github.com/repos/droboports/kernel-drobo5n/releases/assets/894451",
        "id": 894451,
        "name": "cifs.ko",
        "label": null,
        "uploader": {
          "login": "ricardopadilha",
          "id": 1210756,
          "avatar_url": "https://avatars.githubusercontent.com/u/1210756?v=3",
          "gravatar_id": "",
          "url": "https://api.github.com/users/ricardopadilha",
          "html_url": "https://github.com/ricardopadilha",
          "followers_url": "https://api.github.com/users/ricardopadilha/followers",
          "following_url": "https://api.github.com/users/ricardopadilha/following{/other_user}",
          "gists_url": "https://api.github.com/users/ricardopadilha/gists{/gist_id}",
          "starred_url": "https://api.github.com/users/ricardopadilha/starred{/owner}{/repo}",
          "subscriptions_url": "https://api.github.com/users/ricardopadilha/subscriptions",
          "organizations_url": "https://api.github.com/users/ricardopadilha/orgs",
          "repos_url": "https://api.github.com/users/ricardopadilha/repos",
          "events_url": "https://api.github.com/users/ricardopadilha/events{/privacy}",
          "received_events_url": "https://api.github.com/users/ricardopadilha/received_events",
          "type": "User",
          "site_admin": false
        },
        "content_type": "application/octet-stream",
        "state": "uploaded",
        "size": 3547303,
        "download_count": 0,
        "created_at": "2015-09-25T20:06:56Z",
        "updated_at": "2015-09-25T20:07:14Z",
        "browser_download_url": "https://github.com/droboports/kernel-drobo5n/releases/download/v3.2.27-3.2.0/cifs.ko"
      },
      {
        "url": "https://api.github.com/repos/droboports/kernel-drobo5n/releases/assets/894454",
        "id": 894454,
        "name": "crc-itu-t.ko",
        "label": null,
        "uploader": {
          "login": "ricardopadilha",
          "id": 1210756,
          "avatar_url": "https://avatars.githubusercontent.com/u/1210756?v=3",
          "gravatar_id": "",
          "url": "https://api.github.com/users/ricardopadilha",
          "html_url": "https://github.com/ricardopadilha",
          "followers_url": "https://api.github.com/users/ricardopadilha/followers",
          "following_url": "https://api.github.com/users/ricardopadilha/following{/other_user}",
          "gists_url": "https://api.github.com/users/ricardopadilha/gists{/gist_id}",
          "starred_url": "https://api.github.com/users/ricardopadilha/starred{/owner}{/repo}",
          "subscriptions_url": "https://api.github.com/users/ricardopadilha/subscriptions",
          "organizations_url": "https://api.github.com/users/ricardopadilha/orgs",
          "repos_url": "https://api.github.com/users/ricardopadilha/repos",
          "events_url": "https://api.github.com/users/ricardopadilha/events{/privacy}",
          "received_events_url": "https://api.github.com/users/ricardopadilha/received_events",
          "type": "User",
          "site_admin": false
        },
        "content_type": "application/octet-stream",
        "state": "uploaded",
        "size": 25555,
        "download_count": 0,
        "created_at": "2015-09-25T20:06:56Z",
        "updated_at": "2015-09-25T20:07:16Z",
        "browser_download_url": "https://github.com/droboports/kernel-drobo5n/releases/download/v3.2.27-3.2.0/crc-itu-t.ko"
      },
      {
        "url": "https://api.github.com/repos/droboports/kernel-drobo5n/releases/assets/894453",
        "id": 894453,
        "name": "cuse.ko",
        "label": null,
        "uploader": {
          "login": "ricardopadilha",
          "id": 1210756,
          "avatar_url": "https://avatars.githubusercontent.com/u/1210756?v=3",
          "gravatar_id": "",
          "url": "https://api.github.com/users/ricardopadilha",
          "html_url": "https://github.com/ricardopadilha",
          "followers_url": "https://api.github.com/users/ricardopadilha/followers",
          "following_url": "https://api.github.com/users/ricardopadilha/following{/other_user}",
          "gists_url": "https://api.github.com/users/ricardopadilha/gists{/gist_id}",
          "starred_url": "https://api.github.com/users/ricardopadilha/starred{/owner}{/repo}",
          "subscriptions_url": "https://api.github.com/users/ricardopadilha/subscriptions",
          "organizations_url": "https://api.github.com/users/ricardopadilha/orgs",
          "repos_url": "https://api.github.com/users/ricardopadilha/repos",
          "events_url": "https://api.github.com/users/ricardopadilha/events{/privacy}",
          "received_events_url": "https://api.github.com/users/ricardopadilha/received_events",
          "type": "User",
          "site_admin": false
        },
        "content_type": "application/octet-stream",
        "state": "uploaded",
        "size": 123951,
        "download_count": 0,
        "created_at": "2015-09-25T20:06:56Z",
        "updated_at": "2015-09-25T20:07:16Z",
        "browser_download_url": "https://github.com/droboports/kernel-drobo5n/releases/download/v3.2.27-3.2.0/cuse.ko"
      },
      {
        "url": "https://api.github.com/repos/droboports/kernel-drobo5n/releases/assets/894455",
        "id": 894455,
        "name": "ecb.ko",
        "label": null,
        "uploader": {
          "login": "ricardopadilha",
          "id": 1210756,
          "avatar_url": "https://avatars.githubusercontent.com/u/1210756?v=3",
          "gravatar_id": "",
          "url": "https://api.github.com/users/ricardopadilha",
          "html_url": "https://github.com/ricardopadilha",
          "followers_url": "https://api.github.com/users/ricardopadilha/followers",
          "following_url": "https://api.github.com/users/ricardopadilha/following{/other_user}",
          "gists_url": "https://api.github.com/users/ricardopadilha/gists{/gist_id}",
          "starred_url": "https://api.github.com/users/ricardopadilha/starred{/owner}{/repo}",
          "subscriptions_url": "https://api.github.com/users/ricardopadilha/subscriptions",
          "organizations_url": "https://api.github.com/users/ricardopadilha/orgs",
          "repos_url": "https://api.github.com/users/ricardopadilha/repos",
          "events_url": "https://api.github.com/users/ricardopadilha/events{/privacy}",
          "received_events_url": "https://api.github.com/users/ricardopadilha/received_events",
          "type": "User",
          "site_admin": false
        },
        "content_type": "application/octet-stream",
        "state": "uploaded",
        "size": 60825,
        "download_count": 0,
        "created_at": "2015-09-25T20:06:56Z",
        "updated_at": "2015-09-25T20:07:17Z",
        "browser_download_url": "https://github.com/droboports/kernel-drobo5n/releases/download/v3.2.27-3.2.0/ecb.ko"
      },
      {
        "url": "https://api.github.com/repos/droboports/kernel-drobo5n/releases/assets/894457",
        "id": 894457,
        "name": "fuse.ko",
        "label": null,
        "uploader": {
          "login": "ricardopadilha",
          "id": 1210756,
          "avatar_url": "https://avatars.githubusercontent.com/u/1210756?v=3",
          "gravatar_id": "",
          "url": "https://api.github.com/users/ricardopadilha",
          "html_url": "https://github.com/ricardopadilha",
          "followers_url": "https://api.github.com/users/ricardopadilha/followers",
          "following_url": "https://api.github.com/users/ricardopadilha/following{/other_user}",
          "gists_url": "https://api.github.com/users/ricardopadilha/gists{/gist_id}",
          "starred_url": "https://api.github.com/users/ricardopadilha/starred{/owner}{/repo}",
          "subscriptions_url": "https://api.github.com/users/ricardopadilha/subscriptions",
          "organizations_url": "https://api.github.com/users/ricardopadilha/orgs",
          "repos_url": "https://api.github.com/users/ricardopadilha/repos",
          "events_url": "https://api.github.com/users/ricardopadilha/events{/privacy}",
          "received_events_url": "https://api.github.com/users/ricardopadilha/received_events",
          "type": "User",
          "site_admin": false
        },
        "content_type": "application/octet-stream",
        "state": "uploaded",
        "size": 723839,
        "download_count": 0,
        "created_at": "2015-09-25T20:06:56Z",
        "updated_at": "2015-09-25T20:07:28Z",
        "browser_download_url": "https://github.com/droboports/kernel-drobo5n/releases/download/v3.2.27-3.2.0/fuse.ko"
      },
      {
        "url": "https://api.github.com/repos/droboports/kernel-drobo5n/releases/assets/894458",
        "id": 894458,
        "name": "nbd.ko",
        "label": null,
        "uploader": {
          "login": "ricardopadilha",
          "id": 1210756,
          "avatar_url": "https://avatars.githubusercontent.com/u/1210756?v=3",
          "gravatar_id": "",
          "url": "https://api.github.com/users/ricardopadilha",
          "html_url": "https://github.com/ricardopadilha",
          "followers_url": "https://api.github.com/users/ricardopadilha/followers",
          "following_url": "https://api.github.com/users/ricardopadilha/following{/other_user}",
          "gists_url": "https://api.github.com/users/ricardopadilha/gists{/gist_id}",
          "starred_url": "https://api.github.com/users/ricardopadilha/starred{/owner}{/repo}",
          "subscriptions_url": "https://api.github.com/users/ricardopadilha/subscriptions",
          "organizations_url": "https://api.github.com/users/ricardopadilha/orgs",
          "repos_url": "https://api.github.com/users/ricardopadilha/repos",
          "events_url": "https://api.github.com/users/ricardopadilha/events{/privacy}",
          "received_events_url": "https://api.github.com/users/ricardopadilha/received_events",
          "type": "User",
          "site_admin": false
        },
        "content_type": "application/octet-stream",
        "state": "uploaded",
        "size": 207650,
        "download_count": 0,
        "created_at": "2015-09-25T20:06:56Z",
        "updated_at": "2015-09-25T20:07:28Z",
        "browser_download_url": "https://github.com/droboports/kernel-drobo5n/releases/download/v3.2.27-3.2.0/nbd.ko"
      },
      {
        "url": "https://api.github.com/repos/droboports/kernel-drobo5n/releases/assets/894456",
        "id": 894456,
        "name": "nfsd.ko",
        "label": null,
        "uploader": {
          "login": "ricardopadilha",
          "id": 1210756,
          "avatar_url": "https://avatars.githubusercontent.com/u/1210756?v=3",
          "gravatar_id": "",
          "url": "https://api.github.com/users/ricardopadilha",
          "html_url": "https://github.com/ricardopadilha",
          "followers_url": "https://api.github.com/users/ricardopadilha/followers",
          "following_url": "https://api.github.com/users/ricardopadilha/following{/other_user}",
          "gists_url": "https://api.github.com/users/ricardopadilha/gists{/gist_id}",
          "starred_url": "https://api.github.com/users/ricardopadilha/starred{/owner}{/repo}",
          "subscriptions_url": "https://api.github.com/users/ricardopadilha/subscriptions",
          "organizations_url": "https://api.github.com/users/ricardopadilha/orgs",
          "repos_url": "https://api.github.com/users/ricardopadilha/repos",
          "events_url": "https://api.github.com/users/ricardopadilha/events{/privacy}",
          "received_events_url": "https://api.github.com/users/ricardopadilha/received_events",
          "type": "User",
          "site_admin": false
        },
        "content_type": "application/octet-stream",
        "state": "uploaded",
        "size": 1379499,
        "download_count": 3,
        "created_at": "2015-09-25T20:06:56Z",
        "updated_at": "2015-09-25T20:07:25Z",
        "browser_download_url": "https://github.com/droboports/kernel-drobo5n/releases/download/v3.2.27-3.2.0/nfsd.ko"
      },
      {
        "url": "https://api.github.com/repos/droboports/kernel-drobo5n/releases/assets/894459",
        "id": 894459,
        "name": "pcbc.ko",
        "label": null,
        "uploader": {
          "login": "ricardopadilha",
          "id": 1210756,
          "avatar_url": "https://avatars.githubusercontent.com/u/1210756?v=3",
          "gravatar_id": "",
          "url": "https://api.github.com/users/ricardopadilha",
          "html_url": "https://github.com/ricardopadilha",
          "followers_url": "https://api.github.com/users/ricardopadilha/followers",
          "following_url": "https://api.github.com/users/ricardopadilha/following{/other_user}",
          "gists_url": "https://api.github.com/users/ricardopadilha/gists{/gist_id}",
          "starred_url": "https://api.github.com/users/ricardopadilha/starred{/owner}{/repo}",
          "subscriptions_url": "https://api.github.com/users/ricardopadilha/subscriptions",
          "organizations_url": "https://api.github.com/users/ricardopadilha/orgs",
          "repos_url": "https://api.github.com/users/ricardopadilha/repos",
          "events_url": "https://api.github.com/users/ricardopadilha/events{/privacy}",
          "received_events_url": "https://api.github.com/users/ricardopadilha/received_events",
          "type": "User",
          "site_admin": false
        },
        "content_type": "application/octet-stream",
        "state": "uploaded",
        "size": 63950,
        "download_count": 0,
        "created_at": "2015-09-25T20:06:57Z",
        "updated_at": "2015-09-25T20:07:29Z",
        "browser_download_url": "https://github.com/droboports/kernel-drobo5n/releases/download/v3.2.27-3.2.0/pcbc.ko"
      },
      {
        "url": "https://api.github.com/repos/droboports/kernel-drobo5n/releases/assets/894460",
        "id": 894460,
        "name": "tun.ko",
        "label": null,
        "uploader": {
          "login": "ricardopadilha",
          "id": 1210756,
          "avatar_url": "https://avatars.githubusercontent.com/u/1210756?v=3",
          "gravatar_id": "",
          "url": "https://api.github.com/users/ricardopadilha",
          "html_url": "https://github.com/ricardopadilha",
          "followers_url": "https://api.github.com/users/ricardopadilha/followers",
          "following_url": "https://api.github.com/users/ricardopadilha/following{/other_user}",
          "gists_url": "https://api.github.com/users/ricardopadilha/gists{/gist_id}",
          "starred_url": "https://api.github.com/users/ricardopadilha/starred{/owner}{/repo}",
          "subscriptions_url": "https://api.github.com/users/ricardopadilha/subscriptions",
          "organizations_url": "https://api.github.com/users/ricardopadilha/orgs",
          "repos_url": "https://api.github.com/users/ricardopadilha/repos",
          "events_url": "https://api.github.com/users/ricardopadilha/events{/privacy}",
          "received_events_url": "https://api.github.com/users/ricardopadilha/received_events",
          "type": "User",
          "site_admin": false
        },
        "content_type": "application/octet-stream",
        "state": "uploaded",
        "size": 226114,
        "download_count": 1,
        "created_at": "2015-09-25T20:06:57Z",
        "updated_at": "2015-09-25T20:07:30Z",
        "browser_download_url": "https://github.com/droboports/kernel-drobo5n/releases/download/v3.2.27-3.2.0/tun.ko"
      }
    ],
    "tarball_url": "https://api.github.com/repos/droboports/kernel-drobo5n/tarball/v3.2.27-3.2.0",
    "zipball_url": "https://api.github.com/repos/droboports/kernel-drobo5n/zipball/v3.2.27-3.2.0",
    "body": "Kernel configuration updated to firmware 3.2.0.\r\n\r\nSee the [wiki](https://github.com/droboports/kernel-drobo5n/wiki) for compile instructions."
  }
]
