[
  {
    "url": "https://api.github.com/repos/droboports/python-cryptography/releases/1468027",
    "assets_url": "https://api.github.com/repos/droboports/python-cryptography/releases/1468027/assets",
    "upload_url": "https://uploads.github.com/repos/droboports/python-cryptography/releases/1468027/assets{?name,label}",
    "html_url": "https://github.com/droboports/python-cryptography/releases/tag/v0.9.1-fs",
    "id": 1468027,
    "tag_name": "v0.9.1-fs",
    "target_commitish": "drobofs",
    "name": "cryptography 0.9.1 for DroboFS",
    "draft": false,
    "author": {
      "login": "ricardopadilha",
      "id": 1210756,
      "avatar_url": "https://avatars.githubusercontent.com/u/1210756?v=3",
      "gravatar_id": "",
      "url": "https://api.github.com/users/ricardopadilha",
      "html_url": "https://github.com/ricardopadilha",
      "followers_url": "https://api.github.com/users/ricardopadilha/followers",
      "following_url": "https://api.github.com/users/ricardopadilha/following{/other_user}",
      "gists_url": "https://api.github.com/users/ricardopadilha/gists{/gist_id}",
      "starred_url": "https://api.github.com/users/ricardopadilha/starred{/owner}{/repo}",
      "subscriptions_url": "https://api.github.com/users/ricardopadilha/subscriptions",
      "organizations_url": "https://api.github.com/users/ricardopadilha/orgs",
      "repos_url": "https://api.github.com/users/ricardopadilha/repos",
      "events_url": "https://api.github.com/users/ricardopadilha/events{/privacy}",
      "received_events_url": "https://api.github.com/users/ricardopadilha/received_events",
      "type": "User",
      "site_admin": false
    },
    "prerelease": true,
    "created_at": "2015-06-27T02:23:24Z",
    "published_at": "2015-06-27T02:29:27Z",
    "assets": [
      {
        "url": "https://api.github.com/repos/droboports/python-cryptography/releases/assets/670675",
        "id": 670675,
        "name": "cryptography-0.9.1-py2.7-linux-armv5tejl.egg",
        "label": null,
        "uploader": {
          "login": "ricardopadilha",
          "id": 1210756,
          "avatar_url": "https://avatars.githubusercontent.com/u/1210756?v=3",
          "gravatar_id": "",
          "url": "https://api.github.com/users/ricardopadilha",
          "html_url": "https://github.com/ricardopadilha",
          "followers_url": "https://api.github.com/users/ricardopadilha/followers",
          "following_url": "https://api.github.com/users/ricardopadilha/following{/other_user}",
          "gists_url": "https://api.github.com/users/ricardopadilha/gists{/gist_id}",
          "starred_url": "https://api.github.com/users/ricardopadilha/starred{/owner}{/repo}",
          "subscriptions_url": "https://api.github.com/users/ricardopadilha/subscriptions",
          "organizations_url": "https://api.github.com/users/ricardopadilha/orgs",
          "repos_url": "https://api.github.com/users/ricardopadilha/repos",
          "events_url": "https://api.github.com/users/ricardopadilha/events{/privacy}",
          "received_events_url": "https://api.github.com/users/ricardopadilha/received_events",
          "type": "User",
          "site_admin": false
        },
        "content_type": "application/octet-stream",
        "state": "uploaded",
        "size": 828069,
        "download_count": 2,
        "created_at": "2015-06-27T02:29:11Z",
        "updated_at": "2015-06-27T02:29:21Z",
        "browser_download_url": "https://github.com/droboports/python-cryptography/releases/download/v0.9.1-fs/cryptography-0.9.1-py2.7-linux-armv5tejl.egg"
      }
    ],
    "tarball_url": "https://api.github.com/repos/droboports/python-cryptography/tarball/v0.9.1-fs",
    "zipball_url": "https://api.github.com/repos/droboports/python-cryptography/zipball/v0.9.1-fs",
    "body": "Compiled for python 2.7.10. Requires [cffi](https://github.com/droboports/python-cffi/releases) to be installed first."
  },
  {
    "url": "https://api.github.com/repos/droboports/python-cryptography/releases/1467956",
    "assets_url": "https://api.github.com/repos/droboports/python-cryptography/releases/1467956/assets",
    "upload_url": "https://uploads.github.com/repos/droboports/python-cryptography/releases/1467956/assets{?name,label}",
    "html_url": "https://github.com/droboports/python-cryptography/releases/tag/v0.9.1",
    "id": 1467956,
    "tag_name": "v0.9.1",
    "target_commitish": "master",
    "name": "cryptography 0.9.1 for Drobo5N",
    "draft": false,
    "author": {
      "login": "ricardopadilha",
      "id": 1210756,
      "avatar_url": "https://avatars.githubusercontent.com/u/1210756?v=3",
      "gravatar_id": "",
      "url": "https://api.github.com/users/ricardopadilha",
      "html_url": "https://github.com/ricardopadilha",
      "followers_url": "https://api.github.com/users/ricardopadilha/followers",
      "following_url": "https://api.github.com/users/ricardopadilha/following{/other_user}",
      "gists_url": "https://api.github.com/users/ricardopadilha/gists{/gist_id}",
      "starred_url": "https://api.github.com/users/ricardopadilha/starred{/owner}{/repo}",
      "subscriptions_url": "https://api.github.com/users/ricardopadilha/subscriptions",
      "organizations_url": "https://api.github.com/users/ricardopadilha/orgs",
      "repos_url": "https://api.github.com/users/ricardopadilha/repos",
      "events_url": "https://api.github.com/users/ricardopadilha/events{/privacy}",
      "received_events_url": "https://api.github.com/users/ricardopadilha/received_events",
      "type": "User",
      "site_admin": false
    },
    "prerelease": false,
    "created_at": "2015-06-27T01:24:34Z",
    "published_at": "2015-06-27T01:27:08Z",
    "assets": [
      {
        "url": "https://api.github.com/repos/droboports/python-cryptography/releases/assets/670618",
        "id": 670618,
        "name": "cryptography-0.9.1-py2.7-linux-armv7l.egg",
        "label": null,
        "uploader": {
          "login": "ricardopadilha",
          "id": 1210756,
          "avatar_url": "https://avatars.githubusercontent.com/u/1210756?v=3",
          "gravatar_id": "",
          "url": "https://api.github.com/users/ricardopadilha",
          "html_url": "https://github.com/ricardopadilha",
          "followers_url": "https://api.github.com/users/ricardopadilha/followers",
          "following_url": "https://api.github.com/users/ricardopadilha/following{/other_user}",
          "gists_url": "https://api.github.com/users/ricardopadilha/gists{/gist_id}",
          "starred_url": "https://api.github.com/users/ricardopadilha/starred{/owner}{/repo}",
          "subscriptions_url": "https://api.github.com/users/ricardopadilha/subscriptions",
          "organizations_url": "https://api.github.com/users/ricardopadilha/orgs",
          "repos_url": "https://api.github.com/users/ricardopadilha/repos",
          "events_url": "https://api.github.com/users/ricardopadilha/events{/privacy}",
          "received_events_url": "https://api.github.com/users/ricardopadilha/received_events",
          "type": "User",
          "site_admin": false
        },
        "content_type": "application/octet-stream",
        "state": "uploaded",
        "size": 809787,
        "download_count": 13,
        "created_at": "2015-06-27T01:26:39Z",
        "updated_at": "2015-06-27T01:26:44Z",
        "browser_download_url": "https://github.com/droboports/python-cryptography/releases/download/v0.9.1/cryptography-0.9.1-py2.7-linux-armv7l.egg"
      }
    ],
    "tarball_url": "https://api.github.com/repos/droboports/python-cryptography/tarball/v0.9.1",
    "zipball_url": "https://api.github.com/repos/droboports/python-cryptography/zipball/v0.9.1",
    "body": "Compiled for python 2.7.10. Requires [cffi](https://github.com/droboports/python-cffi/releases) to be installed first."
  }
]
